{
  "description": "'''Brill Building''' (also known as '''Brill Building pop''' or the '''Brill Building sound''') is a [[Music subgenre|subgenre]] of [[pop music]] that took its name from the [[Brill Building]] in New York City, where numerous teams of professional songwriters penned material for [[girl group]]s and [[teen idol]]s during the early 1960s. The term has also become a [[metonym]] for the period in which those songwriting teams flourished.{{sfn|Seabrook|2015|p=51}} In actuality, most hits of the mid-1950s and early 1960s were written elsewhere.{{sfn|Seabrook|2015|p=51}}",
  "last_revision_date": "2026-01-11T06:57:56Z",
  "mixes": [
    {
      "playlist": "PLcbZsrmlXdICf9q1lV_GoPNh8JiWSWpjH"
    }
  ],
  "top_artists": [
    "Carole King",
    "Neil Sedaka",
    "Ellie Greenwich",
    "Bobby Vee",
    "Cindy Lee (band)"
  ]
}