{
  "description": "'''Industrial techno''' is a subgenre of [[techno]] and [[industrial dance music]] that originated in the 1990s. Characteristically, it incorporates influences from the bleak, noisy sound and aesthetics of early [[industrial music]] acts, particularly [[Cabaret Voltaire (band)|Cabaret Voltaire]] and [[Throbbing Gristle]]. American industrial music label [[Wax Trax! Records|Wax Trax!]] also had a profound influence over the genre's development.",
  "last_revision_date": "2025-07-29T10:53:33Z",
  "mixes": [
    {
      "video": "YYAT7XVn5Q0"
    }
  ],
  "top_artists": [
    "Surgeon (musician)",
    "Orphx",
    "Blawan",
    "Kill Memory Crash",
    "Tzusing",
    "Joshua Strachan",
    "I Hate Models"
  ]
}