{
  "description": "'''Latin ballad''' ({{langx|es|link=no|balada romántica}}) is a [[sentimental ballad]] derived from [[bolero]] that originated in the early 1960s in Los Angeles, California and [[Southern California]].\n\nSome of the best known artists of the Latin ballad are [[Julio Iglesias]], [[Mocedades]], [[José Luis Rodríguez (singer)|José Luis Rodriguez]], [[Luis Miguel]], [[Camilo Sesto]], [[Emmanuel (singer)|Emmanuel]], [[Nino Bravo]], [[Roberto Carlos (singer)|Roberto Carlos]], [[Ricardo Montaner]], [[Raphael (singer)|Raphael]] and [[José José]] among others. Because of its difficulty, the Latin balladeers are often recognized as skilled singers such as the case of Nino Bravo, Camilo Sesto, José José, Luis Miguel or Raphael.\nIn recent decades it has become the dominant musical genre of Latin pop.",
  "last_revision_date": "2025-04-25T02:56:28Z",
  "mixes": [
    {
      "playlist": "PLq7cLZdz4cAlYJKV1S_GZAGW7xAcesJAr"
    }
  ],
  "top_artists": [
    "Luis Miguel",
    "David Bisbal",
    "Ricardo Arjona",
    "Raphael (singer)",
    "Ana Gabriel",
    "Ednita Nazario",
    "Amanda Miguel",
    "Pepe Aguilar",
    "David Bustamante",
    "Aleks Syntek"
  ]
}