{
  "description": "'''Neue Deutsche Welle''' ('''NDW''', {{IPA|de|ˈnɔʏə ˈdɔʏtʃə ˈvɛlə|pron}}, \"new German wave\") is a [[Music genre|genre]] of [[German rock music|West German rock music]] originally derived from [[post-punk]] and [[New wave music|new wave]] with electronic influences. The term was first coined by Dutch radio DJ Frits Ritmeester on the nationwide radio station [[Hilversum 3]], which was very popular among German listeners. Soon after that, the term was used in a record-shop advertisement by Burkhardt Seiler in an August 1979 issue of the West German magazine ''Sounds''. It was then used by journalist Alfred Hilsberg in an October 1979 ''Sounds'' article about the movement, titled {{lang|de|Neue Deutsche Welle — Aus grauer Städte Mauern}} (\"new German wave—from the walls of grey cities\").",
  "last_revision_date": "2025-12-24T06:47:57Z",
  "mixes": [
    {
      "video": "rHni2q6Uq_A"
    }
  ],
  "top_artists": [
    "Nina Hagen",
    "Nena",
    "Falco (musician)",
    "Nena (band)",
    "Deutsch Amerikanische Freundschaft",
    "Peter Schilling",
    "Trio (band)",
    "Joachim Witt",
    "Uwe Fahrenkrog-Petersen",
    "Der Plan"
  ]
}