{
  "description": "In music, '''montage''' (literally \"putting together\") or '''sound collage''' (\"gluing together\") is a technique where newly branded [[sound object]]s or [[Musical composition|compositions]], including songs, are created from [[collage]], also known as [[musique concrète]]. This is often done through the use of [[sampling (music)|sampling]], while some sound collages are produced by gluing together sectors of different [[vinyl records]]. Like its visual cousin, sound collage works may have a completely different effect than that of the component parts, even if the original parts are recognizable or from a single source. Audio collage was a feature of the [[audio art]] of [[John Cage]], [[Fluxus]], [[postmodern music|postmodern]] [[hip-hop]] and [[postconceptual]] [[digital art]].",
  "last_revision_date": "2025-05-04T21:12:37Z",
  "mixes": [
    {
      "video": "L0wHmTcOZN4"
    }
  ],
  "top_artists": [
    "Negativland",
    "Faust (band)",
    "Jeff Mangum",
    "Vampire Rodents",
    "The Books",
    "People Like Us (musician)",
    "V/Vm",
    "Alan Bishop",
    "Don Joyce (musician)",
    "Longmont Potion Castle"
  ]
}